README.md
setup.py
normal_forms/__init__.py
normal_forms/bases.py
normal_forms/combinatorics.py
normal_forms/jet.py
normal_forms/lie_operator.py
normal_forms/multiindex.py
normal_forms/normal_form.py
normal_forms.egg-info/PKG-INFO
normal_forms.egg-info/SOURCES.txt
normal_forms.egg-info/dependency_links.txt
normal_forms.egg-info/not-zip-safe
normal_forms.egg-info/requires.txt
normal_forms.egg-info/top_level.txt