Metadata-Version: 1.0
Name: normal-forms
Version: 0.4
Summary: Normal forms of dynamical systems
Home-page: https://joepatmckenna.github.io/normal_forms/html
Author: Joseph P. McKenna
Author-email: joepatmckenna@gmail.com
License: MIT
Keywords: normal form differential equation dynamical system bifurcation
Platform: UNKNOWN
